MANIFEST.in
setup.py
docs/CONTRIBUTORS.txt
docs/HISTORY.txt
docs/LICENSE.ZPL
docs/LICENSE.txt
docs/README.txt
docs/sequence.png
docs/sequence.uml
src/ztfy/__init__.py
src/ztfy.media.egg-info/PKG-INFO
src/ztfy.media.egg-info/SOURCES.txt
src/ztfy.media.egg-info/dependency_links.txt
src/ztfy.media.egg-info/entry_points.txt
src/ztfy.media.egg-info/namespace_packages.txt
src/ztfy.media.egg-info/not-zip-safe
src/ztfy.media.egg-info/requires.txt
src/ztfy.media.egg-info/top_level.txt
src/ztfy/media/__init__.py
src/ztfy/media/adapter.py
src/ztfy/media/configure.zcml
src/ztfy/media/converter.py
src/ztfy/media/events.py
src/ztfy/media/ffbase.py
src/ztfy/media/ffdocument.py
src/ztfy/media/ffexception.py
src/ztfy/media/interfaces.py
src/ztfy/media/utility.py
src/ztfy/media/vocabulary.py
src/ztfy/media/browser/__init__.py
src/ztfy/media/browser/configure.zcml
src/ztfy/media/browser/display.py
src/ztfy/media/browser/interfaces.py
src/ztfy/media/browser/preview.py
src/ztfy/media/browser/utility.py
src/ztfy/media/browser/resources/css/ztfy.media.css
src/ztfy/media/browser/resources/css/ztfy.media.min.css
src/ztfy/media/browser/resources/flowplayer/LICENSE.md
src/ztfy/media/browser/resources/flowplayer/embed.min.js
src/ztfy/media/browser/resources/flowplayer/flowplayer.js
src/ztfy/media/browser/resources/flowplayer/flowplayer.min.js
src/ztfy/media/browser/resources/flowplayer/flowplayer.swf
src/ztfy/media/browser/resources/flowplayer/flowplayerhls.swf
src/ztfy/media/browser/resources/flowplayer/index.html
src/ztfy/media/browser/resources/flowplayer/skin/all-skins.css
src/ztfy/media/browser/resources/flowplayer/skin/all-skins.min.css
src/ztfy/media/browser/resources/flowplayer/skin/functional.css
src/ztfy/media/browser/resources/flowplayer/skin/functional.min.css
src/ztfy/media/browser/resources/flowplayer/skin/minimalist.css
src/ztfy/media/browser/resources/flowplayer/skin/minimalist.min.css
src/ztfy/media/browser/resources/flowplayer/skin/playful.css
src/ztfy/media/browser/resources/flowplayer/skin/playful.min.css
src/ztfy/media/browser/resources/flowplayer/skin/fonts/fpicons.eot
src/ztfy/media/browser/resources/flowplayer/skin/fonts/fpicons.svg
src/ztfy/media/browser/resources/flowplayer/skin/fonts/fpicons.ttf
src/ztfy/media/browser/resources/flowplayer/skin/fonts/fpicons.woff
