Metadata-Version: 1.1
Name: ztfy.media
Version: 0.1.12
Summary: ZTFY medias handling package
Home-page: http://hg.ztfy.org/ztfy.media
Author: Thierry Florac
Author-email: tflorac@ulthar.net
License: zpl
Keywords: ZTFY audio video ffmpeg flowplayer
Platform: UNKNOWN
Classifier: Programming Language :: Python
